<?xml version="1.0" encoding="utf-8"?>
<proposicao tipo="REQ       " numero="8196" ano="2013">
  <nomeProposicao>REQ 8196/2013</nomeProposicao>
  <idProposicao>584279</idProposicao>
  <nomeProposicaoOrigem>
  </nomeProposicaoOrigem>
  <tipoProposicao>Requerimento de Moção</tipoProposicao>
  <Ementa>Requeremos, nos termos regimentais da Câmara dos Deputados, a aprovação de Moção de Repúdio ao governo dos Estados Unidos em razão das atividades da National Security Agency (NSA) no País, as quais violam direito de empresas e cidadãos brasileiros e atentam contra a soberania nacional. </Ementa>
  <ExplicacaoEmenta>
  </ExplicacaoEmenta>
  <Autor>José Guimarães</Autor>
  <DataApresentacao>09/07/2013</DataApresentacao>
  <RegimeTramitacao>.</RegimeTramitacao>
  <UltimoDespacho Data="08/08/2013">Encaminhe-se cópia do expediente em epígrafe ao Ministro de Estado das Relações Exteriores. Publique-se. Arquive-se.</UltimoDespacho>
  <Apreciacao>.</Apreciacao>
  <Indexacao>
  </Indexacao>
  <Situacao>MESA - Arquivada</Situacao>
  <LinkInteiroTeor>http://www.camara.gov.br/proposicoesWeb/prop_mostrarintegra?codteor=1107936</LinkInteiroTeor>
  <apensadas />
</proposicao>